mercadopagoCTS/__init__.py
mercadopagoCTS/mercadopagoCTS.py
mercadopagoCTS-1.3.dist-info/LICENSE
mercadopagoCTS-1.3.dist-info/METADATA
mercadopagoCTS-1.3.dist-info/WHEEL
mercadopagoCTS-1.3.dist-info/top_level.txt
mercadopagoCTS-1.3.dist-info/RECORD
